mod9/__init__.py
mod9/asr/__init__.py
mod9/asr/common.py
mod9/asr/speech.py
mod9/asr/speech_mod9.py
mod9/es/client.py
mod9/reformat/config.py
mod9/reformat/google.py
mod9/reformat/utils.py
mod9/rest/server.py
mod9/switchboard/benchmark.py
mod9/websocket/client.py
mod9/websocket/server.py
mod9_asr-1.11.8.dist-info/LICENSE
mod9_asr-1.11.8.dist-info/METADATA
mod9_asr-1.11.8.dist-info/WHEEL
mod9_asr-1.11.8.dist-info/entry_points.txt
mod9_asr-1.11.8.dist-info/top_level.txt
mod9_asr-1.11.8.dist-info/RECORD
