Metadata-Version: 2.1
Name: mod9-asr
Version: 1.11.8
Summary: Mod9 ASR Python SDK, REST API, and Websocket Interface: high-level interfaces to the Mod9 ASR Engine.
Home-page: https://github.com/mod9-asr/python-sdk
Author: Mod9 Technologies
Author-email: support@mod9.com
License: BSD 2-Clause
Platform: UNKNOWN
License-File: LICENSE
Requires-Dist: aiofiles (>=0.5.0)
Requires-Dist: boto3 (>=1.9.0)
Requires-Dist: elasticsearch (>=7.8.1)
Requires-Dist: flask-restful (>=0.3.9)
Requires-Dist: flask (<2.3)
Requires-Dist: google-auth (>=1.22.0)
Requires-Dist: google-cloud-speech (<2.23.0)
Requires-Dist: google-cloud-storage (>=1.30.0)
Requires-Dist: google-resumable-media (>=1.0.0)
Requires-Dist: packaging (>=15.0)
Requires-Dist: proto-plus (>=1.4.0)
Requires-Dist: protobuf (<4)
Requires-Dist: websockets (>=10)
